chalk/__init__.py
chalk/logging.py
chalk/utils.py
nucypher_pychalk-2.0.2.dist-info/licenses/AUTHORS
nucypher_pychalk-2.0.2.dist-info/licenses/LICENSE
nucypher_pychalk-2.0.2.dist-info/METADATA
nucypher_pychalk-2.0.2.dist-info/WHEEL
nucypher_pychalk-2.0.2.dist-info/pbr.json
nucypher_pychalk-2.0.2.dist-info/top_level.txt
nucypher_pychalk-2.0.2.dist-info/RECORD
