Metadata-Version: 2.4
Name: nucypher-pychalk
Version: 2.0.2
Summary: Color printing in python
Home-page: https://github.com/nucypher/pychalk
Author: Anthony Almarza
Author-email: anthony.almarza@gmail.com
License: MIT
Keywords: ascii colors,color,colour,chalk,logging,print
Classifier: Development Status :: 4 - Beta
Classifier: Environment :: Console
Classifier: Intended Audience :: Developers
Classifier: Intended Audience :: Information Technology
Classifier: License :: OSI Approved :: MIT License
Classifier: Operating System :: OS Independent
Classifier: Programming Language :: Python
License-File: LICENSE
License-File: AUTHORS
Requires-Dist: six>=1.11.0
Dynamic: author
Dynamic: author-email
Dynamic: classifier
Dynamic: description
Dynamic: description-content-type
Dynamic: home-page
Dynamic: keywords
Dynamic: license
Dynamic: license-file
Dynamic: requires-dist
Dynamic: summary
